MANIFEST.in
README.txt
cirrus.conf
requirements.txt
setup.py
src/pyfile_to_module/__init__.py
src/pyfile_to_module/pyfile_to_module.py
src/pyfile_to_module.egg-info/PKG-INFO
src/pyfile_to_module.egg-info/SOURCES.txt
src/pyfile_to_module.egg-info/dependency_links.txt
src/pyfile_to_module.egg-info/entry_points.txt
src/pyfile_to_module.egg-info/top_level.txt