Metadata-Version: 1.1
Name: pyfile-to-module
Version: 0.0.4
Summary: Util for converting system path names into python module names
Home-page: https://github.com/evansde77/pyfile_to_module
Author: evansde77
Author-email: evansde77.github@gmail.com
License: UNKNOWN
Platform: UNKNOWN
Provides: pyfile_to_module
